scripts/__init__.py
scripts/add_license.py
scripts/check_license_headers.py
semantiva_imaging-0.2.1.dist-info/METADATA
semantiva_imaging-0.2.1.dist-info/WHEEL
semantiva_imaging-0.2.1.dist-info/entry_points.txt
semantiva_imaging-0.2.1.dist-info/licenses/LICENSE
semantiva_imaging-0.2.1.dist-info/licenses/NOTICE
semantiva_imaging/README.md
semantiva_imaging/__init__.py
semantiva_imaging/adapters/__init__.py
semantiva_imaging/adapters/factory.py
semantiva_imaging/adapters/opencv_factory.py
semantiva_imaging/adapters/opencv_library/__init__.py
semantiva_imaging/adapters/opencv_library/builders.py
semantiva_imaging/adapters/opencv_library/filters.py
semantiva_imaging/adapters/opencv_library/morphology.py
semantiva_imaging/adapters/opencv_library/transforms.py
semantiva_imaging/data_io/__init__.py
semantiva_imaging/data_io/io.py
semantiva_imaging/data_io/loaders_savers.py
semantiva_imaging/data_io/parametric_base.py
semantiva_imaging/data_io/parametric_line.py
semantiva_imaging/data_io/parametric_surface.py
semantiva_imaging/data_io/url_loader.py
semantiva_imaging/data_types/__init__.py
semantiva_imaging/data_types/data_types.py
semantiva_imaging/data_types/mpl_figure.py
semantiva_imaging/probes/__init__.py
semantiva_imaging/probes/probes.py
semantiva_imaging/processing/__init__.py
semantiva_imaging/processing/base_nchannel.py
semantiva_imaging/processing/figure_render.py
semantiva_imaging/processing/operations.py
semantiva_imaging/processing/processors.py
semantiva_imaging/py.typed
semantiva_imaging/visualization/__init__.py
semantiva_imaging/visualization/viewers.py
semantiva_imaging-0.2.1.dist-info/RECORD
