Metadata-Version: 2.4
Name: semantiva-imaging
Version: 0.2.1
Summary: Image extension of Semantiva framework.
License-Expression: Apache-2.0
Requires-Python: >=3.10.12
Requires-Dist: numpy>=1.23.0
Requires-Dist: semantiva>=0.5.0
Requires-Dist: pillow>=9.2.0
Requires-Dist: scipy>=1.9.0
Requires-Dist: matplotlib>=3.6.0
Requires-Dist: ipywidgets>=8.0.0
Requires-Dist: opencv-python>=4.8.0
